esi_extern_openquake/__init__.py
esi_extern_openquake/geodetic.py
esi_extern_openquake/point.py
esi_extern_openquake/utils.py
esi_extern_openquake-1.0.2.dist-info/LICENSE.md
esi_extern_openquake-1.0.2.dist-info/WHEEL
esi_extern_openquake-1.0.2.dist-info/METADATA
esi_extern_openquake-1.0.2.dist-info/RECORD
